<?xml version="1.0" encoding="utf-8"?>
<SoundBanksInfo Platform="Windows" BasePlatform="Windows" SchemaVersion="16" SoundBankVersion="150">
	<SoundBanks>
		<SoundBank Id="3161908922" Type="User" GUID="{629FAB7B-C345-4463-854D-D8C6F1A181C2}" Language="SFX" Hash="{BE6B8E7E-2F83-8DCC-4A63-F2B73895496B}">
			<ObjectPath>\SoundBanks\Default Work Unit\Main</ObjectPath>
			<ShortName>Main</ShortName>
			<Path>Main.bnk</Path>
			<Media>
				<File Id="434028665" Language="SFX" Streaming="false" Location="Memory">
					<ShortName>auto_attack_dist_temp.wav</ShortName>
					<CachePath>SFX/auto_attack_dist_temp_818F3B66.wem</CachePath>
				</File>
			</Media>
			<Events>
				<Event Id="3987506369" Name="AttackDistTest" ObjectPath="\Events\Default Work Unit\AttackDistTest" GUID="{CD759F51-5E65-482F-8D8E-5541A2C00105}" DurationType="OneShot" DurationMin="0.48898414" DurationMax="0.48898414">
					<MediaRefs>
						<MediaRef Id="434028665"/>
					</MediaRefs>
				</Event>
			</Events>
		</SoundBank>
	</SoundBanks>
	<FileHash>{559B5E8B-46DC-3F1B-8EDC-5A746F031AF7}</FileHash>
</SoundBanksInfo>
